colorama/__init__.py
colorama/ansi.py
colorama/ansitowin32.py
colorama/initialise.py
colorama/win32.py
colorama/winterm.py
colorama-0.4.2.dist-info/LICENSE.txt
colorama-0.4.2.dist-info/METADATA
colorama-0.4.2.dist-info/WHEEL
colorama-0.4.2.dist-info/top_level.txt
colorama-0.4.2.dist-info/RECORD
